setup.py
tohaml
tohaml.py
tohaml.egg-info/PKG-INFO
tohaml.egg-info/SOURCES.txt
tohaml.egg-info/dependency_links.txt
tohaml.egg-info/requires.txt
tohaml.egg-info/top_level.txt