Metadata-Version: 1.0
Name: tohaml
Version: 1.0a
Summary: converts html to haml
Home-page: http://github.com/boscoh/tohaml
Author: Bosco Ho
Author-email: boscoh@gmail.com
License: BSD
Platform: UNKNOWN
